[
    {
        "name": "Jens Peters",
        "website_url": "https://jenspeters.substack.com",
        "rss_url": "https://jenspeters.substack.com/feed/",
        "description": "never not [thinking about] running! Das ist das Motto des Blogs. Jens befindet sich gerade auf dem Weg sein erstes UTMB-Event zu laufen und berichtet, sehr persöhnlich, über diese Reise."
    },
    {
        "name": "Harlerunner",
        "website_url": "https://harlerunner.de",
        "rss_url": "https://harlerunner.de/feed/",
        "description": "Auf Harlerunner.de schreibt Thomas Pier über das Laufen und (deutlich mehr als nur die notwendige) Ausrüstung. Tests neuer Laufuhren sind dort genauso zufinden wie der Test neuer Sensoren oder Schuhe."
    }
]
